audomo/__main__.py
CHANGELOG.md
audomo-0.1.0.dist-info/entry_points.txt
audomo-0.1.0.dist-info/LICENSE
audomo-0.1.0.dist-info/METADATA
audomo-0.1.0.dist-info/WHEEL
audomo-0.1.0.dist-info/RECORD
